moptipy/__init__.py
moptipy/py.typed
moptipy/version.py
moptipy/algorithms/__init__.py
moptipy/algorithms/luby_restarts.py
moptipy/algorithms/random_sampling.py
moptipy/algorithms/random_walk.py
moptipy/algorithms/restarts.py
moptipy/algorithms/single_random_sample.py
moptipy/algorithms/mo/__init__.py
moptipy/algorithms/mo/morls.py
moptipy/algorithms/mo/nsga2.py
moptipy/algorithms/modules/__init__.py
moptipy/algorithms/modules/selection.py
moptipy/algorithms/modules/temperature_schedule.py
moptipy/algorithms/modules/selections/__init__.py
moptipy/algorithms/modules/selections/best.py
moptipy/algorithms/modules/selections/fitness_proportionate_sus.py
moptipy/algorithms/modules/selections/random_without_repl.py
moptipy/algorithms/modules/selections/tournament_with_repl.py
moptipy/algorithms/modules/selections/tournament_without_repl.py
moptipy/algorithms/so/__init__.py
moptipy/algorithms/so/ea.py
moptipy/algorithms/so/fitness.py
moptipy/algorithms/so/general_ea.py
moptipy/algorithms/so/general_ma.py
moptipy/algorithms/so/greedy_2plus1_ea_mod.py
moptipy/algorithms/so/hill_climber.py
moptipy/algorithms/so/hill_climber_with_restarts.py
moptipy/algorithms/so/ma.py
moptipy/algorithms/so/marls.py
moptipy/algorithms/so/ppa.py
moptipy/algorithms/so/record.py
moptipy/algorithms/so/rls.py
moptipy/algorithms/so/simulated_annealing.py
moptipy/algorithms/so/ffa/__init__.py
moptipy/algorithms/so/ffa/eafea.py
moptipy/algorithms/so/ffa/eafea_a.py
moptipy/algorithms/so/ffa/eafea_b.py
moptipy/algorithms/so/ffa/eafea_c.py
moptipy/algorithms/so/ffa/eafea_d.py
moptipy/algorithms/so/ffa/eafea_n.py
moptipy/algorithms/so/ffa/fea1plus1.py
moptipy/algorithms/so/ffa/ffa_fitness.py
moptipy/algorithms/so/ffa/ffa_h.py
moptipy/algorithms/so/ffa/ffa_hill_climber.py
moptipy/algorithms/so/ffa/safea_a.py
moptipy/algorithms/so/ffa/safea_b.py
moptipy/algorithms/so/ffa/safea_n.py
moptipy/algorithms/so/fitnesses/__init__.py
moptipy/algorithms/so/fitnesses/direct.py
moptipy/algorithms/so/fitnesses/rank.py
moptipy-0.9.164.dist-info/licenses/LICENSE
moptipy-0.9.164.dist-info/METADATA
moptipy-0.9.164.dist-info/WHEEL
moptipy-0.9.164.dist-info/top_level.txt
moptipy-0.9.164.dist-info/RECORD
