Metadata-Version: 2.4
Name: moptipy
Version: 0.9.164
Summary: A package for metaheuristic optimization in Python.
Home-page: https://thomasweise.github.io/moptipy
Author: Thomas Weise
Author-email: tweise@ustc.edu.cn
Maintainer: Thomas Weise
Maintainer-email: tweise@ustc.edu.cn
License: GPL 3.0
Project-URL: Documentation, https://thomasweise.github.io/moptipy
Project-URL: Source, https://github.com/thomasWeise/moptipy/
Project-URL: Tracker, https://github.com/thomasWeise/moptipy/issues
Keywords: algorithm performance evaluation,BGFS,BOBYQA,continuous optimization,crossover,DE,Differential Evolution,discrete optimization,EA,ECDF,Empirical Cumulative Distribution Function,ERT,Evolutionary Algorithm,Evolutionary Computation,Expected Running Time,experiments,Frequency Fitness Assignment,Hill Climber,Job Shop Scheduling Problem,JSSP,metaheuristics,Memetic Algorithm,multi-objective optimization,mutation,NSGA-II,optimization,operations research,performance plots,permutations,Plant Pr
Classifier: Development Status :: 4 - Beta
Classifier: Framework :: Matplotlib
Classifier: Intended Audience :: Developers
Classifier: Intended Audience :: Education
Classifier: Intended Audience :: Science/Research
Classifier: Natural Language :: English
Classifier: Natural Language :: German
Classifier: Natural Language :: Chinese (Simplified)
Classifier: Operating System :: Microsoft :: Windows
Classifier: Operating System :: POSIX :: Linux
Classifier: Programming Language :: Python :: 3 :: Only
Classifier: Programming Language :: Python :: 3.12
Classifier: Topic :: Education
Classifier: Topic :: Scientific/Engineering :: Artificial Intelligence
Classifier: Topic :: Scientific/Engineering :: Mathematics
Classifier: Topic :: Scientific/Engineering :: Visualization
Requires-Python: >=3.12
License-File: LICENSE
Requires-Dist: cmaes>=0.12.0
Requires-Dist: intel-cmplr-lib-rt>=2025.3.1
Requires-Dist: numpy>=2.3.5
Requires-Dist: numba>=0.63.0
Requires-Dist: matplotlib>=3.10.7
Requires-Dist: pdfo>=2.2.0
Requires-Dist: psutil>=7.1.3
Requires-Dist: pycommons>=0.8.81
Requires-Dist: scikit-learn>=1.7.2
Requires-Dist: scipy>=1.16.3
Dynamic: description
Dynamic: description-content-type
Dynamic: license-file
